murmur/clients/swarm/__init__.py
murmur/clients/swarm/swarm_agent.py
murmur_swarm-0.0.4.dist-info/METADATA
murmur_swarm-0.0.4.dist-info/WHEEL
murmur_swarm-0.0.4.dist-info/RECORD
